{
    "$schema": "https://schema.management.azure.com/schemas/2018-05-01/subscriptionDeploymentTemplate.json#",
    "contentVersion": "1.0.0.0",
    "parameters": {
        "mspOfferName": {
            "type": "string",
            "defaultValue": "Sentor Managed Security Services"
        },
        "mspOfferDescription": {
            "type": "string",
            "defaultValue": "Sentor Managed Security Services"
        },
        "managedByTenantId": {
            "type": "string",
            "defaultValue": "6f8d0bce-eebe-4abb-a14f-9d036c3e9626"
        },
        "authorizations": {
            "type": "array",
            "defaultValue": [
                {
                    "principalId": "68671c17-4e50-4880-975f-671097aba943",
                    "roleDefinitionId": "b24988ac-6180-42a0-ab88-20f7382dd24c",
                    "principalIdDisplayName": "SOC"
                },
                {
                    "principalId": "93bcc35d-995b-42a3-9193-6945d3f93a7d",
                    "principalIdDisplayName": "MSSP Admin",
                    "roleDefinitionId": "18d7d88d-d35e-4fb5-a5c3-7773c20a72d9",
                    "delegatedRoleDefinitionIds": [
                        "b24988ac-6180-42a0-ab88-20f7382dd24c",
                        "f4c81013-99ee-4d62-a7ee-b3f1f648599a",
                        "ab8e14d6-4a74-4a29-9ba8-549422addade",
                        "92aaf0da-9dab-42b6-94a3-d43ce8d16293",
                        "91c1777a-f3dc-4fae-b103-61d183457e46"
                    ]
                },
                {
                    "principalId": "987dc622-4cf5-4eb6-aeee-980fc2706a60",
                    "principalIdDisplayName": "MSSP Registration Manager",
                    "roleDefinitionId": "91c1777a-f3dc-4fae-b103-61d183457e46"
                }
            ]
        }
    },
    "variables": {
        "mspRegistrationName": "[guid(parameters('mspOfferName'))]",
        "mspAssignmentName": "[guid(parameters('mspOfferName'))]"
    },
    "resources": [
        {
            "type": "Microsoft.ManagedServices/registrationDefinitions",
            "apiVersion": "2019-09-01",
            "name": "[variables('mspRegistrationName')]",
            "properties": {
                "registrationDefinitionName": "[parameters('mspOfferName')]",
                "description": "[parameters('mspOfferDescription')]",
                "managedByTenantId": "[parameters('managedByTenantId')]",
                "authorizations": "[parameters('authorizations')]"
            }
        },
        {
            "type": "Microsoft.ManagedServices/registrationAssignments",
            "apiVersion": "2019-09-01",
            "name": "[variables('mspAssignmentName')]",
            "dependsOn": [
                "[resourceId('Microsoft.ManagedServices/registrationDefinitions/', variables('mspRegistrationName'))]"
            ],
            "properties": {
                "registrationDefinitionId": "[resourceId('Microsoft.ManagedServices/registrationDefinitions/', variables('mspRegistrationName'))]"
            }
        }
    ],
    "outputs": {
        "mspOfferName": {
            "type": "string",
            "value": "[concat('Managed by', ' ', parameters('mspOfferName'))]"
        },
        "authorizations": {
            "type": "array",
            "value": "[parameters('authorizations')]"
        }
    }
}
